gaussidan/__init__.py
gaussidan/fit_gaussian.py
gaussidan/plot_gaussian.py
gaussidan-0.1.5.dist-info/WHEEL
gaussidan-0.1.5.dist-info/METADATA
gaussidan-0.1.5.dist-info/RECORD
